LICENSE.txt
MANIFEST.in
README.rst
requirements.txt
setup.py
accountable/__init__.py
accountable/accountable.py
accountable/cli.py
accountable/config.py
accountable.egg-info/PKG-INFO
accountable.egg-info/SOURCES.txt
accountable.egg-info/dependency_links.txt
accountable.egg-info/entry_points.txt
accountable.egg-info/requires.txt
accountable.egg-info/top_level.txt