Metadata-Version: 1.0
Name: accountable
Version: 0.1
Summary: Command line tools for interacting with JIRA
Home-page: https://github.com/wohlgejm/accountable
Author: Jerry Wohlgemuth
Author-email: wohlgejm@gmail.com
License: MIT
Keywords: jira
Platform: UNKNOWN
